{
    "oneOf": [
        {
            "required": [
                "repList"
            ],
            "type": "object",
            "properties": {
                "repList": {
                    "required": [
                        "containers"
                    ],
                    "type": "object",
                    "properties": {
                        "containers": {
                            "uniqueItems": false,
                            "items": {
                                "type": "string"
                            },
                            "type": "array"
                        }
                    }
                }
            }
        },
        {
            "required": [
                "repStdout"
            ],
            "type": "object",
            "properties": {
                "repStdout": {
                    "required": [
                        "stdoutContainerUUUID",
                        "stdoutPayload"
                    ],
                    "type": "object",
                    "properties": {
                        "stdoutPayload": {
                            "type": "string"
                        },
                        "stdoutContainerUUUID": {
                            "type": "string"
                        }
                    }
                }
            }
        },
        {
            "required": [
                "repStderr"
            ],
            "type": "object",
            "properties": {
                "repStderr": {
                    "required": [
                        "stderrContainerID",
                        "stderrPayload"
                    ],
                    "type": "object",
                    "properties": {
                        "stderrPayload": {
                            "type": "string"
                        },
                        "stderrContainerID": {
                            "type": "string"
                        }
                    }
                }
            }
        },
        {
            "required": [
                "repStart"
            ],
            "type": "object",
            "properties": {
                "repStart": {
                    "required": [
                        "startContainerID",
                        "pid"
                    ],
                    "type": "object",
                    "properties": {
                        "startContainerID": {
                            "type": "string"
                        },
                        "pid": {
                            "type": "number"
                        }
                    }
                }
            }
        },
        {
            "required": [
                "repProcessExit"
            ],
            "type": "object",
            "properties": {
                "repProcessExit": {
                    "required": [
                        "container_uuid",
                        "status"
                    ],
                    "type": "object",
                    "properties": {
                        "status": {
                            "type": "number"
                        },
                        "container_uuid": {
                            "type": "string"
                        }
                    }
                }
            }
        },
        {
            "required": [
                "repGetPower"
            ],
            "type": "object",
            "properties": {
                "repGetPower": {
                    "required": [
                        "limit"
                    ],
                    "type": "object",
                    "properties": {
                        "limit": {
                            "type": "number"
                        }
                    }
                }
            }
        }
    ]
}